fast_di/__init__.py
fast_di/init_dependencies.py
fast_di/collector/__init__.py
fast_di/collector/base.py
fast_di/collector/collector.py
fast_di/depends/__init__.py
fast_di/depends/depends.py
fast_di/depends/depends_stub.py
fastapi_di_extension-0.0.3.dist-info/LICENSE
fastapi_di_extension-0.0.3.dist-info/METADATA
fastapi_di_extension-0.0.3.dist-info/WHEEL
fastapi_di_extension-0.0.3.dist-info/top_level.txt
fastapi_di_extension-0.0.3.dist-info/RECORD
